par_cc_usage/__init__.py
par_cc_usage/__main__.py
par_cc_usage/commands.py
par_cc_usage/config.py
par_cc_usage/display.py
par_cc_usage/emoji_config.py
par_cc_usage/enums.py
par_cc_usage/file_monitor.py
par_cc_usage/json_analyzer.py
par_cc_usage/json_models.py
par_cc_usage/list_command.py
par_cc_usage/main.py
par_cc_usage/models.py
par_cc_usage/notification_manager.py
par_cc_usage/options.py
par_cc_usage/pricing.py
par_cc_usage/statusline_manager.py
par_cc_usage/summary_calculator.py
par_cc_usage/summary_display.py
par_cc_usage/theme.py
par_cc_usage/token_calculator.py
par_cc_usage/utils.py
par_cc_usage/webhook_client.py
par_cc_usage/xdg_dirs.py
par_cc_usage-0.12.0.dist-info/METADATA
par_cc_usage-0.12.0.dist-info/WHEEL
par_cc_usage-0.12.0.dist-info/entry_points.txt
par_cc_usage-0.12.0.dist-info/licenses/LICENSE
par_cc_usage-0.12.0.dist-info/RECORD
