Metadata-Version: 2.4
Name: par-cc-usage
Version: 0.12.0
Summary: Claude Code usage tracking tool with real-time monitoring and analysis
Project-URL: Homepage, https://github.com/paulrobello/par_cc_usage
Project-URL: Documentation, https://github.com/paulrobello/par_cc_usage/blob/main/README.md
Project-URL: Source, https://github.com/paulrobello/par_cc_usage
Project-URL: Issues, https://github.com/paulrobello/par_cc_usage/issues
Author-email: Paul Robello <probello@gmail.com>
Maintainer-email: Paul Robello <probello@gmail.com>
License: MIT License
License-File: LICENSE
Keywords: anthropic,claude,claude-code,cli,monitoring,real-time,terminal,token-usage,usage-tracking
Classifier: Development Status :: 4 - Beta
Classifier: Environment :: Console
Classifier: Intended Audience :: Developers
Classifier: Intended Audience :: End Users/Desktop
Classifier: License :: OSI Approved :: MIT License
Classifier: Operating System :: MacOS
Classifier: Operating System :: Microsoft :: Windows :: Windows 10
Classifier: Operating System :: Microsoft :: Windows :: Windows 11
Classifier: Operating System :: POSIX :: Linux
Classifier: Programming Language :: Python :: 3
Classifier: Programming Language :: Python :: 3.11
Classifier: Programming Language :: Python :: 3.12
Classifier: Programming Language :: Python :: 3.13
Classifier: Topic :: Scientific/Engineering :: Artificial Intelligence
Classifier: Topic :: Software Development :: Libraries :: Python Modules
Classifier: Topic :: System :: Monitoring
Classifier: Topic :: Terminals
Classifier: Typing :: Typed
Requires-Python: >=3.11
Requires-Dist: aiofiles>=23.0.0
Requires-Dist: aiohttp>=3.9.0
Requires-Dist: pydantic>=2.0.0
Requires-Dist: pytz>=2023.3
Requires-Dist: pyyaml>=6.0.1
Requires-Dist: requests>=2.31.0
Requires-Dist: rich>=13.7.0
Requires-Dist: typer>=0.9.0
Requires-Dist: watchdog>=3.0.0
Requires-Dist: xdg-base-dirs>=6.0.2
